{
  "courses": [
    {
      "title": "ASP.NET Core Masterclass",
      "description": "Master ASP.NET Core from scratch to advanced. Build production-grade REST APIs, implement authentication, work with databases using Entity Framework Core, and deploy to the cloud. This course covers real-world scenarios and best practices used in the industry.",
      "shortDescription": "Build production-grade APIs with ASP.NET Core",
      "price": 49.99,
      "discountPrice": 39.99,
      "level": "Intermediate",
      "language": "English",
      "thumbnailUrl": "https://img.youtube.com/vi/AhAxLiGC7Pc/maxresdefault.jpg",
      "subCategorySlug": "web-development",
      "instructorEmail": "sara.ahmed@guidy.com",
      "requirements": [
        "Basic C# knowledge",
        "Understanding of OOP concepts",
        "Visual Studio or VS Code installed"
      ],
      "whatYouLearn": [
        "Build RESTful APIs with ASP.NET Core",
        "Implement JWT authentication",
        "Work with Entity Framework Core",
        "Deploy to Azure"
      ],
      "sections": [
        {
          "title": "Getting Started",
          "lessons": [
            {
              "title": "Course Introduction",
              "description": "Overview of what we will build in this course.",
              "videoUrl": "https://youtu.be/P1j1PI0YL-M?si=PZnTmxctNTExpGbK",
              "durationInSeconds": 47,
              "type": "Video",
              "isFreePreview": true
            },
            {
              "title": "Setting Up Development Environment",
              "description": "Install .NET SDK, Visual Studio, and required tools.",
              "videoUrl": "https://youtu.be/TxaZYXtZWCM?si=epNu3t500kmhTwry",
              "durationInSeconds": 1800,
              "type": "Video",
              "isFreePreview": true
            },
            {
              "title": "Your First ASP.NET Core App",
              "description": "Create and run your first ASP.NET Core application.",
              "videoUrl": "https://youtu.be/t2aMZFzV3jI?si=TS5fGFuFtvAA5imG",
              "durationInSeconds": 2324,
              "type": "Video",
              "isFreePreview": false
            }
          ]
        },
        {
          "title": "Building REST APIs",
          "lessons": [
            {
              "title": "Controllers and Routing",
              "description": "Deep dive into controllers, actions, and routing.",
              "videoUrl": "https://youtu.be/j87UkenRf7k?si=iiwIgDMMSqp4G-b9",
              "durationInSeconds": 1666,
              "type": "Video",
              "isFreePreview": false
            },
            {
              "title": "HTTP Methods and Status Codes",
              "description": "GET, POST, PUT, PATCH, DELETE — when to use each.",
              "videoUrl": "https://youtu.be/XTB3V6R1L-c?si=fMMy1GQrLZc7y3tS",
              "durationInSeconds": 1462,
              "type": "Video",
              "isFreePreview": false
            },
            {
              "title": "REST API Quiz",
              "description": "Test your understanding of REST API concepts.",
              "videoUrl": null,
              "durationInSeconds": 0,
              "type": "Quiz",
              "isFreePreview": false
            }
          ]
        },
        {
          "title": "Entity Framework Core",
          "lessons": [
            {
              "title": "Introduction to EF Core",
              "description": "What is an ORM and why use EF Core.",
              "videoUrl": "https://youtu.be/eOqTJWuCXho?si=hfFspoOKfkKHMRmY",
              "durationInSeconds": 4272,
              "type": "Video",
              "isFreePreview": false
            },
            {
              "title": "Code First Approach",
              "description": "Create your database from C# classes.",
              "videoUrl": "https://youtu.be/ByIQf4VS2d4?si=kxJPJVIZS8ZWFb2f",
              "durationInSeconds": 3180,
              "type": "Video",
              "isFreePreview": false
            },
            {
              "title": "Querying with LINQ",
              "description": "Use LINQ to query your database efficiently.",
              "videoUrl": "https://youtu.be/LEhv_owDo0o?si=dHWBporebvpcTpZd",
              "durationInSeconds": 2580,
              "type": "Video",
              "isFreePreview": false
            }
          ]
        },
        {
          "title": "Authentication and Authorization",
          "lessons": [
            {
              "title": "JWT Authentication Explained",
              "description": "Understand how JWT tokens work.",
              "videoUrl": "https://youtu.be/F3ryldPGQoM?si=B3TaxQdw_esDh4XW",
              "durationInSeconds": 1560,
              "type": "Video",
              "isFreePreview": false
            },
            {
              "title": "Implementing JWT in ASP.NET Core",
              "description": "Add JWT authentication to your API step by step.",
              "videoUrl": "https://youtu.be/-gWx_NILonQ?si=mLQxgt9ucaDM7MxI",
              "durationInSeconds": 960,
              "type": "Video",
              "isFreePreview": false
            },
            {
              "title": "Role-Based Authorization",
              "description": "Restrict endpoints based on user roles.",
              "videoUrl": "https://youtu.be/3pbfQ-ZDoyc?si=znnBq7bKJQnZ-QTb",
              "durationInSeconds": 1920,
              "type": "Video",
              "isFreePreview": false
            }
          ]
        }
      ]
    },
    {
      "title": "Clean Architecture in .NET",
      "description": "Learn how to structure .NET applications using Clean Architecture principles. Covers CQRS, MediatR, Repository Pattern, Unit of Work, Specification Pattern, and Domain-Driven Design with hands-on projects.",
      "shortDescription": "Professional .NET project structure with Clean Architecture",
      "price": 59.99,
      "discountPrice": null,
      "level": "Advanced",
      "language": "English",
      "thumbnailUrl": "https://img.youtube.com/vi/dI5B3gZa9tY/maxresdefault.jpg",
      "subCategorySlug": "software-engineering",
      "instructorEmail": "sara.ahmed@guidy.com",
      "requirements": [
        "Intermediate C# skills",
        "Experience with ASP.NET Core",
        "Basic understanding of design patterns"
      ],
      "whatYouLearn": [
        "Implement Clean Architecture",
        "Apply CQRS with MediatR",
        "Use Repository and Unit of Work patterns",
        "Write clean and maintainable code"
      ],
      "sections": [
        {
          "title": "Clean Architecture Fundamentals",
          "lessons": [
            {
              "title": "What is Clean Architecture?",
              "description": "Understand the layers and principles.",
              "videoUrl": "https://www.youtube.com/watch?v=dI5B3gZa9tY",
              "durationInSeconds": 1240,
              "type": "Video",
              "isFreePreview": true
            },
            {
              "title": "The Dependency Rule",
              "description": "The most important rule in Clean Architecture.",
              "videoUrl": "https://www.youtube.com/watch?v=dI5B3gZa9tY",
              "durationInSeconds": 890,
              "type": "Video",
              "isFreePreview": true
            },
            {
              "title": "Setting Up the Solution Structure",
              "description": "Create the project structure step by step.",
              "videoUrl": "https://www.youtube.com/watch?v=dI5B3gZa9tY",
              "durationInSeconds": 1540,
              "type": "Video",
              "isFreePreview": false
            }
          ]
        },
        {
          "title": "CQRS with MediatR",
          "lessons": [
            {
              "title": "Introduction to CQRS",
              "description": "Why separate Commands from Queries.",
              "videoUrl": "https://www.youtube.com/watch?v=dI5B3gZa9tY",
              "durationInSeconds": 780,
              "type": "Video",
              "isFreePreview": false
            },
            {
              "title": "Writing Commands and Queries",
              "description": "Create Commands, Queries, Handlers and Validators.",
              "videoUrl": "https://www.youtube.com/watch?v=dI5B3gZa9tY",
              "durationInSeconds": 1340,
              "type": "Video",
              "isFreePreview": false
            },
            {
              "title": "Pipeline Behaviors",
              "description": "Add logging and validation as pipeline behaviors.",
              "videoUrl": "https://www.youtube.com/watch?v=dI5B3gZa9tY",
              "durationInSeconds": 1560,
              "type": "Video",
              "isFreePreview": false
            }
          ]
        },
        {
          "title": "Repository and Specification Pattern",
          "lessons": [
            {
              "title": "Generic Repository Pattern",
              "description": "Build a generic repository for any entity.",
              "videoUrl": "https://www.youtube.com/watch?v=dI5B3gZa9tY",
              "durationInSeconds": 1780,
              "type": "Video",
              "isFreePreview": false
            },
            {
              "title": "Specification Pattern",
              "description": "Create reusable query specifications.",
              "videoUrl": "https://www.youtube.com/watch?v=dI5B3gZa9tY",
              "durationInSeconds": 1430,
              "type": "Video",
              "isFreePreview": false
            }
          ]
        }
      ]
    },
    {
      "title": "React for Beginners",
      "description": "Start your frontend journey with React. Learn components, state management, hooks, routing, and how to connect your React app to a backend API. Build real projects from scratch.",
      "shortDescription": "Learn React from zero to hero",
      "price": 44.99,
      "discountPrice": 34.99,
      "level": "Beginner",
      "language": "English",
      "thumbnailUrl": "https://img.youtube.com/vi/Ke90Tje7VS0/maxresdefault.jpg",
      "subCategorySlug": "web-development",
      "instructorEmail": "omar.khaled@guidy.com",
      "requirements": [

        "Basic HTML and CSS",
        "Basic JavaScript knowledge",
        "A code editor installed"
      ],
      "whatYouLearn": [
        "Build React components",
        "Manage state with useState and useReducer",
        "Fetch data from APIs",
        "Build a complete React application"
      ],
      "sections": [
        {
          "title": "React Basics",
          "lessons": [
            {
              "title": "What is React?",
              "description": "Introduction to React and why it exists.",
              "videoUrl": "https://www.youtube.com/watch?v=Ke90Tje7VS0",
              "durationInSeconds": 540,
              "type": "Video",
              "isFreePreview": true
            },
            {
              "title": "Components and Props",
              "description": "Build and reuse components with props.",
              "videoUrl": "https://www.youtube.com/watch?v=Ke90Tje7VS0",
              "durationInSeconds": 1120,
              "type": "Video",
              "isFreePreview": true
            },
            {
              "title": "State with useState",
              "description": "Manage component state using the useState hook.",
              "videoUrl": "https://www.youtube.com/watch?v=Ke90Tje7VS0",
              "durationInSeconds": 1340,
              "type": "Video",
              "isFreePreview": false
            }
          ]
        },
        {
          "title": "React Hooks",
          "lessons": [
            {
              "title": "useEffect Hook",
              "description": "Handle side effects in functional components.",
              "videoUrl": "https://www.youtube.com/watch?v=Ke90Tje7VS0",
              "durationInSeconds": 1560,
              "type": "Video",
              "isFreePreview": false
            },
            {
              "title": "useContext Hook",
              "description": "Share state across components without prop drilling.",
              "videoUrl": "https://www.youtube.com/watch?v=Ke90Tje7VS0",
              "durationInSeconds": 980,
              "type": "Video",
              "isFreePreview": false
            },
            {
              "title": "Custom Hooks",
              "description": "Create your own reusable hooks.",
              "videoUrl": "https://www.youtube.com/watch?v=Ke90Tje7VS0",
              "durationInSeconds": 1230,
              "type": "Video",
              "isFreePreview": false
            }
          ]
        },
        {
          "title": "Connecting to APIs",
          "lessons": [
            {
              "title": "Fetch API and Axios",
              "description": "Make HTTP requests from React.",
              "videoUrl": "https://www.youtube.com/watch?v=Ke90Tje7VS0",
              "durationInSeconds": 890,
              "type": "Video",
              "isFreePreview": false
            },
            {
              "title": "Building a Full CRUD App",
              "description": "Connect to a real backend and build a complete CRUD app.",
              "videoUrl": "https://www.youtube.com/watch?v=Ke90Tje7VS0",
              "durationInSeconds": 2340,
              "type": "Video",
              "isFreePreview": false
            }
          ]
        }
      ]
    },
    {
      "title": "Python for Data Science",
      "description": "Learn Python specifically for data science and machine learning. Covers NumPy, Pandas, Matplotlib, Seaborn, and an introduction to Scikit-learn. Work with real datasets throughout the course.",
      "shortDescription": "Python, Pandas, NumPy, and ML basics",
      "price": 54.99,
      "discountPrice": 44.99,
      "level": "Beginner",
      "language": "English",
      "thumbnailUrl": "https://img.youtube.com/vi/_uQrJ0TkZlc/maxresdefault.jpg",
      "subCategorySlug": "data-analysis",
      "instructorEmail": "mohamed.hassan@guidy.com",
      "requirements": [
        "No prior programming experience needed",
        "A computer with internet access"
      ],
      "whatYouLearn": [
        "Python programming basics",
        "Data manipulation with Pandas",
        "Data visualization with Matplotlib",
        "Introduction to Machine Learning"
      ],
      "sections": [
        {
          "title": "Python Fundamentals",
          "lessons": [
            {
              "title": "Python Introduction",
              "description": "Why Python for data science.",
              "videoUrl": "https://www.youtube.com/watch?v=_uQrJ0TkZlc",
              "durationInSeconds": 780,
              "type": "Video",
              "isFreePreview": true
            },
            {
              "title": "Variables and Data Types",
              "description": "Numbers, strings, lists, and dictionaries.",
              "videoUrl": "https://www.youtube.com/watch?v=_uQrJ0TkZlc",
              "durationInSeconds": 1340,
              "type": "Video",
              "isFreePreview": true
            },
            {
              "title": "Control Flow",
              "description": "If statements, loops, and functions in Python.",
              "videoUrl": "https://www.youtube.com/watch?v=_uQrJ0TkZlc",
              "durationInSeconds": 1560,
              "type": "Video",
              "isFreePreview": false
            }
          ]
        },
        {
          "title": "NumPy and Pandas",
          "lessons": [
            {
              "title": "Introduction to NumPy",
              "description": "Arrays, operations, and mathematical functions.",
              "videoUrl": "https://www.youtube.com/watch?v=_uQrJ0TkZlc",
              "durationInSeconds": 1120,
              "type": "Video",
              "isFreePreview": false
            },
            {
              "title": "Pandas DataFrames",
              "description": "Load, manipulate, and analyze data with Pandas.",
              "videoUrl": "https://www.youtube.com/watch?v=_uQrJ0TkZlc",
              "durationInSeconds": 1890,
              "type": "Video",
              "isFreePreview": false
            },
            {
              "title": "Data Cleaning",
              "description": "Handle missing values, duplicates, and outliers.",
              "videoUrl": "https://www.youtube.com/watch?v=_uQrJ0TkZlc",
              "durationInSeconds": 1560,
              "type": "Video",
              "isFreePreview": false
            }
          ]
        },
        {
          "title": "Data Visualization",
          "lessons": [
            {
              "title": "Matplotlib Basics",
              "description": "Create line charts, bar charts, and scatter plots.",
              "videoUrl": "https://www.youtube.com/watch?v=_uQrJ0TkZlc",
              "durationInSeconds": 980,
              "type": "Video",
              "isFreePreview": false
            },
            {
              "title": "Seaborn for Statistical Plots",
              "description": "Beautiful statistical visualizations.",
              "videoUrl": "https://www.youtube.com/watch?v=_uQrJ0TkZlc",
              "durationInSeconds": 1120,
              "type": "Video",
              "isFreePreview": false
            }
          ]
        }
      ]
    },
    {
      "title": "Machine Learning with Scikit-Learn",
      "description": "Dive into machine learning with hands-on projects. Learn supervised and unsupervised learning, model evaluation, feature engineering, and deploy your first ML model.",
      "shortDescription": "Hands-on ML with Python and Scikit-learn",
      "price": 69.99,
      "discountPrice": null,
      "level": "Intermediate",
      "language": "English",
      "thumbnailUrl": "https://img.youtube.com/vi/7eh4d6sabA0/maxresdefault.jpg",
      "subCategorySlug": "machine-learning",
      "instructorEmail": "mohamed.hassan@guidy.com",
      "requirements": [
        "Python basics",
        "Basic statistics knowledge",
        "Completed Python for Data Science or equivalent"
      ],
      "whatYouLearn": [
        "Supervised learning algorithms",
        "Model evaluation and tuning",
        "Feature engineering",
        "Deploy ML models"
      ],
      "sections": [
        {
          "title": "ML Fundamentals",
          "lessons": [
            {
              "title": "What is Machine Learning?",
              "description": "Types of ML and real-world applications.",
              "videoUrl": "https://www.youtube.com/watch?v=7eh4d6sabA0",
              "durationInSeconds": 890,
              "type": "Video",
              "isFreePreview": true
            },
            {
              "title": "Setting Up Scikit-Learn",
              "description": "Install and configure your ML environment.",
              "videoUrl": "https://www.youtube.com/watch?v=7eh4d6sabA0",
              "durationInSeconds": 540,
              "type": "Video",
              "isFreePreview": true
            }
          ]
        },
        {
          "title": "Supervised Learning",
          "lessons": [
            {
              "title": "Linear Regression",
              "description": "Predict continuous values with linear regression.",
              "videoUrl": "https://www.youtube.com/watch?v=7eh4d6sabA0",
              "durationInSeconds": 1780,
              "type": "Video",
              "isFreePreview": false
            },
            {
              "title": "Decision Trees and Random Forests",
              "description": "Tree-based models for classification and regression.",
              "videoUrl": "https://www.youtube.com/watch?v=7eh4d6sabA0",
              "durationInSeconds": 2100,
              "type": "Video",
              "isFreePreview": false
            }
          ]
        },
        {
          "title": "Model Evaluation",
          "lessons": [
            {
              "title": "Train-Test Split",
              "description": "Properly evaluate your model performance.",
              "videoUrl": "https://www.youtube.com/watch?v=7eh4d6sabA0",
              "durationInSeconds": 780,
              "type": "Video",
              "isFreePreview": false
            },
            {
              "title": "Cross Validation",
              "description": "More robust model evaluation techniques.",
              "videoUrl": "https://www.youtube.com/watch?v=7eh4d6sabA0",
              "durationInSeconds": 980,
              "type": "Video",
              "isFreePreview": false
            },
            {
              "title": "Confusion Matrix and Metrics",
              "description": "Accuracy, precision, recall, F1-score explained.",
              "videoUrl": "https://www.youtube.com/watch?v=7eh4d6sabA0",
              "durationInSeconds": 1120,
              "type": "Video",
              "isFreePreview": false
            }
          ]
        }
      ]
    },
    {
      "title": "Docker and Kubernetes Fundamentals",
      "description": "Learn containerization with Docker and orchestration with Kubernetes. Build, ship, and run applications in containers. Deploy to a Kubernetes cluster and manage microservices at scale.",
      "shortDescription": "Containers, Docker, and Kubernetes from scratch",
      "price": 64.99,
      "discountPrice": 49.99,
      "level": "Intermediate",
      "language": "English",
      "thumbnailUrl": "https://img.youtube.com/vi/fqMOX6JJhGo/maxresdefault.jpg",
      "subCategorySlug": "devops",
      "instructorEmail": "nour.ibrahim@guidy.com",
      "requirements": [
        "Basic Linux command line",
        "Understanding of web applications",
        "A computer with 8GB+ RAM"
      ],
      "whatYouLearn": [
        "Build and run Docker containers",
        "Write Docker Compose files",
        "Deploy to Kubernetes",
        "Manage microservices"
      ],
      "sections": [
        {
          "title": "Docker Basics",
          "lessons": [
            {
              "title": "What is Docker?",
              "description": "Containers vs VMs and why Docker matters.",
              "videoUrl": "https://www.youtube.com/watch?v=fqMOX6JJhGo",
              "durationInSeconds": 780,
              "type": "Video",
              "isFreePreview": true
            },
            {
              "title": "Your First Container",
              "description": "Pull an image and run your first container.",
              "videoUrl": "https://www.youtube.com/watch?v=fqMOX6JJhGo",
              "durationInSeconds": 890,
              "type": "Video",
              "isFreePreview": true
            },
            {
              "title": "Writing Dockerfiles",
              "description": "Create custom Docker images for your apps.",
              "videoUrl": "https://www.youtube.com/watch?v=fqMOX6JJhGo",
              "durationInSeconds": 1340,
              "type": "Video",
              "isFreePreview": false
            },
            {
              "title": "Docker Compose",
              "description": "Define multi-container apps with a single file.",
              "videoUrl": "https://www.youtube.com/watch?v=fqMOX6JJhGo",
              "durationInSeconds": 1890,
              "type": "Video",
              "isFreePreview": false
            }
          ]
        },
        {
          "title": "Kubernetes",
          "lessons": [
            {
              "title": "Kubernetes Architecture",
              "description": "Nodes, pods, services, and deployments explained.",
              "videoUrl": "https://www.youtube.com/watch?v=fqMOX6JJhGo",
              "durationInSeconds": 1560,
              "type": "Video",
              "isFreePreview": false
            },
            {
              "title": "Deploying to Kubernetes",
              "description": "Deploy your first app to a K8s cluster.",
              "videoUrl": "https://www.youtube.com/watch?v=fqMOX6JJhGo",
              "durationInSeconds": 2100,
              "type": "Video",
              "isFreePreview": false
            }
          ]
        }
      ]
    },
    {
      "title": "SQL and Database Design",
      "description": "Learn SQL from the ground up and master database design. Write complex queries, design normalized schemas, work with stored procedures, and optimize query performance.",
      "shortDescription": "Master SQL and database design from scratch",
      "price": 39.99,
      "discountPrice": 29.99,
      "level": "Beginner",
      "language": "English",
      "thumbnailUrl": "https://img.youtube.com/vi/HXV3zeQKqGY/maxresdefault.jpg",
      "subCategorySlug": "data-analysis",
      "instructorEmail": "youssef.adel@guidy.com",
      "requirements": [
        "No prior database experience",
        "Basic computer skills"
      ],
      "whatYouLearn": [
        "Write SQL queries",
        "Design normalized databases",
        "Use JOINs and subqueries",
        "Optimize query performance"
      ],
      "sections": [
        {
          "title": "SQL Basics",
          "lessons": [
            {
              "title": "What is SQL?",
              "description": "Relational databases and SQL overview.",
              "videoUrl": "https://www.youtube.com/watch?v=HXV3zeQKqGY",
              "durationInSeconds": 540,
              "type": "Video",
              "isFreePreview": true
            },
            {
              "title": "SELECT Queries",
              "description": "Retrieve data from tables with SELECT.",
              "videoUrl": "https://www.youtube.com/watch?v=HXV3zeQKqGY",
              "durationInSeconds": 890,
              "type": "Video",
              "isFreePreview": true
            },
            {
              "title": "INSERT UPDATE DELETE",
              "description": "Modify data in your database.",
              "videoUrl": "https://www.youtube.com/watch?v=HXV3zeQKqGY",
              "durationInSeconds": 1120,
              "type": "Video",
              "isFreePreview": false
            }
          ]
        },
        {
          "title": "Advanced SQL",
          "lessons": [
            {
              "title": "JOINs Explained",
              "description": "INNER, LEFT, RIGHT, and FULL JOINs.",
              "videoUrl": "https://www.youtube.com/watch?v=HXV3zeQKqGY",
              "durationInSeconds": 1560,
              "type": "Video",
              "isFreePreview": false
            },
            {
              "title": "Aggregate Functions",
              "description": "COUNT, SUM, AVG, MIN, MAX with GROUP BY.",
              "videoUrl": "https://www.youtube.com/watch?v=HXV3zeQKqGY",
              "durationInSeconds": 1120,
              "type": "Video",
              "isFreePreview": false
            }
          ]
        },
        {
          "title": "Database Design",
          "lessons": [
            {
              "title": "Normalization",
              "description": "1NF, 2NF, 3NF — design clean databases.",
              "videoUrl": "https://www.youtube.com/watch?v=HXV3zeQKqGY",
              "durationInSeconds": 1340,
              "type": "Video",
              "isFreePreview": false
            },
            {
              "title": "Indexes and Performance",
              "description": "Speed up queries with proper indexing.",
              "videoUrl": "https://www.youtube.com/watch?v=HXV3zeQKqGY",
              "durationInSeconds": 1120,
              "type": "Video",
              "isFreePreview": false
            }
          ]
        }
      ]
    },
    {
      "title": "Deep Learning with TensorFlow",
      "description": "Go beyond traditional ML and dive into deep learning. Build neural networks from scratch, implement CNNs for image recognition, RNNs for sequence data, and deploy models to production.",
      "shortDescription": "Neural networks and deep learning with TensorFlow",
      "price": 79.99,
      "discountPrice": 64.99,
      "level": "Advanced",
      "language": "English",
      "thumbnailUrl": "https://img.youtube.com/vi/tPYj3fFJGjk/maxresdefault.jpg",
      "subCategorySlug": "deep-learning",
      "instructorEmail": "mohamed.hassan@guidy.com",
      "requirements": [
        "Python proficiency",
        "Machine learning basics",
        "Linear algebra fundamentals"
      ],
      "whatYouLearn": [
        "Build neural networks with TensorFlow",
        "Implement CNNs and RNNs",
        "Train models on real datasets",
        "Deploy deep learning models"
      ],
      "sections": [
        {
          "title": "Neural Network Basics",
          "lessons": [
            {
              "title": "What are Neural Networks?",
              "description": "Neurons, layers, and how networks learn.",
              "videoUrl": "https://www.youtube.com/watch?v=tPYj3fFJGjk",
              "durationInSeconds": 1340,
              "type": "Video",
              "isFreePreview": true
            },
            {
              "title": "Activation Functions",
              "description": "ReLU, Sigmoid, Softmax — when to use each.",
              "videoUrl": "https://www.youtube.com/watch?v=tPYj3fFJGjk",
              "durationInSeconds": 980,
              "type": "Video",
              "isFreePreview": false
            }
          ]
        },
        {
          "title": "TensorFlow and Keras",
          "lessons": [
            {
              "title": "Building Your First Neural Network",
              "description": "Sequential model with Keras step by step.",
              "videoUrl": "https://www.youtube.com/watch?v=tPYj3fFJGjk",
              "durationInSeconds": 1780,
              "type": "Video",
              "isFreePreview": false
            },
            {
              "title": "Training and Evaluation",
              "description": "Train, validate, and evaluate your model.",
              "videoUrl": "https://www.youtube.com/watch?v=tPYj3fFJGjk",
              "durationInSeconds": 1340,
              "type": "Video",
              "isFreePreview": false
            }
          ]
        },
        {
          "title": "Convolutional Neural Networks",
          "lessons": [
            {
              "title": "CNN Architecture",
              "description": "Convolution, pooling, and fully connected layers.",
              "videoUrl": "https://www.youtube.com/watch?v=tPYj3fFJGjk",
              "durationInSeconds": 1890,
              "type": "Video",
              "isFreePreview": false
            },
            {
              "title": "Image Classification Project",
              "description": "Build a CNN that recognizes handwritten digits.",
              "videoUrl": "https://www.youtube.com/watch?v=tPYj3fFJGjk",
              "durationInSeconds": 2340,
              "type": "Video",
              "isFreePreview": false
            }
          ]
        }
      ]
    },
    {
      "title": "Entrepreneurship 101",
      "description": "Start your entrepreneurial journey with this practical guide. Learn how to validate your business idea, build an MVP, find your first customers, and grow a sustainable business.",
      "shortDescription": "From idea to business — practical entrepreneurship guide",
      "price": 34.99,
      "discountPrice": null,
      "level": "Beginner",
      "language": "English",
      "thumbnailUrl": "https://img.youtube.com/vi/ZoqgAy3h4OM/maxresdefault.jpg",
      "subCategorySlug": "entrepreneurship",
      "instructorEmail": "sara.ahmed@guidy.com",
      "requirements": [
        "No prior business experience needed",
        "An entrepreneurial mindset"
      ],
      "whatYouLearn": [
        "Validate your business idea",
        "Build an MVP",
        "Find your first customers",
        "Create a business model"
      ],
      "sections": [
        {
          "title": "Finding Your Idea",
          "lessons": [
            {
              "title": "Identifying Problems Worth Solving",
              "description": "How to find business opportunities.",
              "videoUrl": "https://www.youtube.com/watch?v=ZoqgAy3h4OM",
              "durationInSeconds": 1120,
              "type": "Video",
              "isFreePreview": true
            },
            {
              "title": "Idea Validation Framework",
              "description": "Validate your idea before building anything.",
              "videoUrl": "https://www.youtube.com/watch?v=ZoqgAy3h4OM",
              "durationInSeconds": 1560,
              "type": "Video",
              "isFreePreview": false
            }
          ]
        },
        {
          "title": "Building Your MVP",
          "lessons": [
            {
              "title": "What is an MVP?",
              "description": "Minimum Viable Product explained with examples.",
              "videoUrl": "https://www.youtube.com/watch?v=ZoqgAy3h4OM",
              "durationInSeconds": 780,
              "type": "Video",
              "isFreePreview": false
            },
            {
              "title": "Getting Your First Customers",
              "description": "Strategies to acquire your first 10 customers.",
              "videoUrl": "https://www.youtube.com/watch?v=ZoqgAy3h4OM",
              "durationInSeconds": 1340,
              "type": "Video",
              "isFreePreview": false
            }
          ]
        }
      ]
    },
    {
      "title": "Introduction to Programming — Free",
      "description": "A completely free introduction to programming for absolute beginners. No prior experience needed. Learn the fundamental concepts of programming using simple examples and exercises.",
      "shortDescription": "Free programming course for absolute beginners",
      "price": 0,
      "discountPrice": null,
      "level": "Beginner",
      "language": "English",
      "thumbnailUrl": "https://img.youtube.com/vi/zOjov-2OZ0E/maxresdefault.jpg",
      "subCategorySlug": "web-development",
      "instructorEmail": "omar.khaled@guidy.com",
      "requirements": [
        "No experience needed",
        "A computer with internet access"
      ],
      "whatYouLearn": [
        "What is programming",
        "Variables and data types",
        "Conditions and loops",
        "Functions and basic algorithms"
      ],
      "sections": [
        {
          "title": "Programming Concepts",
          "lessons": [
            {
              "title": "What is Programming?",
              "description": "Introduction to programming and computers.",
              "videoUrl": "https://www.youtube.com/watch?v=zOjov-2OZ0E",
              "durationInSeconds": 480,
              "type": "Video",
              "isFreePreview": true
            },
            {
              "title": "Variables and Data Types",
              "description": "Store and manipulate data in programs.",
              "videoUrl": "https://www.youtube.com/watch?v=zOjov-2OZ0E",
              "durationInSeconds": 720,
              "type": "Video",
              "isFreePreview": true
            },
            {
              "title": "Conditions and Loops",
              "description": "Make decisions and repeat actions in code.",
              "videoUrl": "https://www.youtube.com/watch?v=zOjov-2OZ0E",
              "durationInSeconds": 840,
              "type": "Video",
              "isFreePreview": true
            }
          ]
        },
        {
          "title": "Functions and Algorithms",
          "lessons": [
            {
              "title": "Functions",
              "description": "Write reusable blocks of code.",
              "videoUrl": "https://www.youtube.com/watch?v=zOjov-2OZ0E",
              "durationInSeconds": 960,
              "type": "Video",
              "isFreePreview": true
            },
            {
              "title": "Basic Algorithms",
              "description": "Sorting, searching, and problem solving.",
              "videoUrl": "https://www.youtube.com/watch?v=zOjov-2OZ0E",
              "durationInSeconds": 1080,
              "type": "Video",
              "isFreePreview": true
            }
          ]
        }
      ]
    }
  ]
}